py4k_means/__init__.py
py4k_means/cluster.py
py4k_means-0.0.1.dist-info/METADATA
py4k_means-0.0.1.dist-info/WHEEL
py4k_means-0.0.1.dist-info/top_level.txt
py4k_means-0.0.1.dist-info/RECORD
